pz_collective/Collection.py
pz_collective/Queryable.py
pz_collective/__init__.py
pz_collective-1.0.0.dist-info/METADATA
pz_collective-1.0.0.dist-info/WHEEL
pz_collective-1.0.0.dist-info/licenses/LICENSE
pz_collective-1.0.0.dist-info/RECORD
