Metadata-Version: 2.4
Name: pz-collective
Version: 1.0.0
Summary: Versatile Python package that brings powerful, C#-like collection and query capabilities to your projects.
Project-URL: Homepage, https://github.com/poziel/collective
Project-URL: Issues, https://github.com/poziel/collective
Author-email: Alexandre Sauvé <alexandre.sauve.dev@gmail.com>
License-File: LICENSE
Classifier: License :: OSI Approved :: MIT License
Classifier: Operating System :: OS Independent
Classifier: Programming Language :: Python :: 3
Requires-Python: >=3.0
